vibegit/__init__.py
vibegit/server.py
vibegit/store.py
vibegit_mcp-0.1.6.dist-info/METADATA
vibegit_mcp-0.1.6.dist-info/WHEEL
vibegit_mcp-0.1.6.dist-info/entry_points.txt
vibegit_mcp-0.1.6.dist-info/top_level.txt
vibegit_mcp-0.1.6.dist-info/RECORD
