Metadata-Version: 2.4
Name: vibegit-mcp
Version: 0.1.6
Summary: VibeGit MCP server for AI conversation logging and analysis
Author-email: VibeGit Team <wjg172184@163.com>
License: MIT
Project-URL: Homepage, https://pypi.org/project/vibegit-mcp
Project-URL: Repository, https://github.com/gixia-org/VibeGit
Keywords: mcp,ai,conversation,logging,assistant
Classifier: Development Status :: 3 - Alpha
Classifier: Intended Audience :: Developers
Classifier: Programming Language :: Python :: 3
Classifier: Programming Language :: Python :: 3.9
Classifier: Programming Language :: Python :: 3.10
Classifier: Programming Language :: Python :: 3.11
Classifier: Programming Language :: Python :: 3.12
Classifier: Topic :: Software Development :: Libraries :: Python Modules
Classifier: Topic :: Communications :: Chat
Requires-Python: >=3.9
Requires-Dist: mcp>=1.14.0
Requires-Dist: anyio>=4.5.0
